icakad/__init__.py
icakad/__main__.py
icakad/ai.py
icakad/cli.py
icakad/config.py
icakad/paste.py
icakad/shorturl.py
icakad/common/__init__.py
icakad-0.1.2.dist-info/licenses/LICENSE
icakad-0.1.2.dist-info/METADATA
icakad-0.1.2.dist-info/WHEEL
icakad-0.1.2.dist-info/top_level.txt
icakad-0.1.2.dist-info/RECORD
