Metadata-Version: 2.4
Name: icakad
Version: 0.1.2
Summary: Utilities and tools for my apis and other life hacks.
Author: icakad
License-Expression: MIT
Project-URL: Homepage, https://saitana.icu/
Project-URL: Repository, https://github.com/icakad97/icakad
Project-URL: ShortURL, https://linkove.icu/
Project-URL: LLAMA_LLM, https://llama.icaka.eu
Keywords: icakad
Classifier: Programming Language :: Python :: 3
Classifier: Programming Language :: Python :: 3.8
Classifier: Programming Language :: Python :: 3.9
Classifier: Programming Language :: Python :: 3.10
Classifier: Programming Language :: Python :: 3.11
Classifier: Programming Language :: Python :: 3.12
Classifier: Topic :: Internet :: WWW/HTTP
Classifier: Topic :: Software Development :: Libraries :: Python Modules
Requires-Python: >=3.8
License-File: LICENSE
Requires-Dist: requests>=2.28
Dynamic: license-file
